README
setup.cfg
setup.py
prompt/__init__.py
prompt/main.py
prompt/runTests.sh
prompt/version
prompt/classes/__init__.py
prompt/classes/apiEndpoint/ApiEndpoint.py
prompt/classes/apiEndpoint/__init__.py
prompt/classes/authentication/AuthenticationInfo.py
prompt/classes/authentication/AuthenticationService.py
prompt/classes/authentication/AuthenticationStorage.py
prompt/classes/authentication/__init__.py
prompt/classes/chat/Chat.py
prompt/classes/chat/Message.py
prompt/classes/chat/__init__.py
prompt/tests/__init__.py
prompt/tests/authentication/TestAuthenticationService.py
prompt/tests/authentication/TestAuthenticationStorage.py
prompt/tests/authentication/__init__.py
prompt/tests/chat/TestChat.py
prompt/tests/chat/__init__.py
promptapp.egg-info/PKG-INFO
promptapp.egg-info/SOURCES.txt
promptapp.egg-info/dependency_links.txt
promptapp.egg-info/entry_points.txt
promptapp.egg-info/requires.txt
promptapp.egg-info/top_level.txt