Metadata-Version: 1.1
Name: promptapp
Version: 0.0.1.dev6
Summary: Prompt CLI
Home-page: https://promptapp.io
Author: Prompt Developers
Author-email: info@promptapp.io
License: Closed
Keywords: prompt bot cli
Platform: UNKNOWN
Classifier: Development Status :: 3 - Alpha
Classifier: Intended Audience :: Developers
Classifier: Topic :: Software Development :: Build Tools
Classifier: License :: OSI Approved :: MIT License
Classifier: Programming Language :: Python :: 2
Classifier: Programming Language :: Python :: 2.6
Classifier: Programming Language :: Python :: 2.7
Classifier: Programming Language :: Python :: 3
Classifier: Programming Language :: Python :: 3.3
Classifier: Programming Language :: Python :: 3.4
Classifier: Programming Language :: Python :: 3.5
